pkrhistoryloader/__init__.py
pkrhistoryloader/app.py
pkrhistoryloader/daily_upload.py
pkrhistoryloader/frequent_upload.py
pkrhistoryloader/loader.py
pkrhistoryloader-1.0.0.dist-info/LICENSE.txt
pkrhistoryloader-1.0.0.dist-info/METADATA
pkrhistoryloader-1.0.0.dist-info/WHEEL
pkrhistoryloader-1.0.0.dist-info/top_level.txt
pkrhistoryloader-1.0.0.dist-info/RECORD
